{
	"cmake" : 
	{
		"generator" : 
		{
			"multiConfig" : false,
			"name" : "Ninja"
		},
		"paths" : 
		{
			"cmake" : "/Applications/Qt/Tools/CMake/CMake.app/Contents/bin/cmake",
			"cpack" : "/Applications/Qt/Tools/CMake/CMake.app/Contents/bin/cpack",
			"ctest" : "/Applications/Qt/Tools/CMake/CMake.app/Contents/bin/ctest",
			"root" : "/Applications/Qt/Tools/CMake/CMake.app/Contents/share/cmake-3.29"
		},
		"version" : 
		{
			"isDirty" : false,
			"major" : 3,
			"minor" : 29,
			"patch" : 3,
			"string" : "3.29.3",
			"suffix" : ""
		}
	},
	"objects" : 
	[
		{
			"jsonFile" : "codemodel-v2-b1d04fb9be904991b70f.json",
			"kind" : "codemodel",
			"version" : 
			{
				"major" : 2,
				"minor" : 7
			}
		},
		{
			"jsonFile" : "cache-v2-2ae2f8a1de31b91c7a26.json",
			"kind" : "cache",
			"version" : 
			{
				"major" : 2,
				"minor" : 0
			}
		},
		{
			"jsonFile" : "cmakeFiles-v1-2660ee9d0250a1b9d831.json",
			"kind" : "cmakeFiles",
			"version" : 
			{
				"major" : 1,
				"minor" : 0
			}
		}
	],
	"reply" : 
	{
		"cache-v2" : 
		{
			"jsonFile" : "cache-v2-2ae2f8a1de31b91c7a26.json",
			"kind" : "cache",
			"version" : 
			{
				"major" : 2,
				"minor" : 0
			}
		},
		"cmakeFiles-v1" : 
		{
			"jsonFile" : "cmakeFiles-v1-2660ee9d0250a1b9d831.json",
			"kind" : "cmakeFiles",
			"version" : 
			{
				"major" : 1,
				"minor" : 0
			}
		},
		"codemodel-v2" : 
		{
			"jsonFile" : "codemodel-v2-b1d04fb9be904991b70f.json",
			"kind" : "codemodel",
			"version" : 
			{
				"major" : 2,
				"minor" : 7
			}
		}
	}
}
